{
  "$schema": "https://developer.microsoft.com/json-schemas/fabric/item/report/definition/visualContainer/2.1.0/schema.json",
  "name": "c3b3aed6c60d5d9a69b4",
  "position": {
    "x": 243.75,
    "y": 0,
    "z": 2000,
    "height": 327.5,
    "width": 880,
    "tabOrder": 2000
  },
  "visual": {
    "visualType": "cardVisual",
    "query": {
      "queryState": {
        "Data": {
          "projections": [
            {
              "field": {
                "Aggregation": {
                  "Expression": {
                    "Column": {
                      "Expression": {
                        "SourceRef": {
                          "Entity": "cleaned_dataset"
                        }
                      },
                      "Property": "total_revenue"
                    }
                  },
                  "Function": 0
                }
              },
              "queryRef": "Sum(cleaned_dataset.total_revenue)",
              "nativeQueryRef": "Sum of total_revenue"
            },
            {
              "field": {
                "Aggregation": {
                  "Expression": {
                    "Column": {
                      "Expression": {
                        "SourceRef": {
                          "Entity": "cleaned_dataset"
                        }
                      },
                      "Property": "profit"
                    }
                  },
                  "Function": 0
                }
              },
              "queryRef": "Sum(cleaned_dataset.profit)",
              "nativeQueryRef": "Sum of profit"
            },
            {
              "field": {
                "Aggregation": {
                  "Expression": {
                    "Column": {
                      "Expression": {
                        "SourceRef": {
                          "Entity": "cleaned_dataset"
                        }
                      },
                      "Property": "quantity_sold"
                    }
                  },
                  "Function": 0
                }
              },
              "queryRef": "Sum(cleaned_dataset.quantity_sold)",
              "nativeQueryRef": "Sum of quantity_sold"
            },
            {
              "field": {
                "Measure": {
                  "Expression": {
                    "SourceRef": {
                      "Entity": "cleaned_dataset"
                    }
                  },
                  "Property": "AVERAGE RATING"
                }
              },
              "queryRef": "cleaned_dataset.AVERAGE RATING",
              "nativeQueryRef": "AVERAGE RATING"
            },
            {
              "field": {
                "Measure": {
                  "Expression": {
                    "SourceRef": {
                      "Entity": "cleaned_dataset"
                    }
                  },
                  "Property": "PROFIT MARGIN %"
                }
              },
              "queryRef": "cleaned_dataset.PROFIT MARGIN %",
              "nativeQueryRef": "PROFIT MARGIN %"
            }
          ]
        }
      },
      "sortDefinition": {
        "sort": [
          {
            "field": {
              "Aggregation": {
                "Expression": {
                  "Column": {
                    "Expression": {
                      "SourceRef": {
                        "Entity": "cleaned_dataset"
                      }
                    },
                    "Property": "total_revenue"
                  }
                },
                "Function": 0
              }
            },
            "direction": "Descending"
          }
        ]
      }
    },
    "objects": {
      "layout": [
        {
          "properties": {
            "orientation": {
              "expr": {
                "Literal": {
                  "Value": "0D"
                }
              }
            },
            "rowCount": {
              "expr": {
                "Literal": {
                  "Value": "2L"
                }
              }
            },
            "columnCount": {
              "expr": {
                "Literal": {
                  "Value": "3L"
                }
              }
            }
          }
        },
        {
          "properties": {
            "rectangleRoundedCurve": {
              "expr": {
                "Literal": {
                  "Value": "48L"
                }
              }
            },
            "rectangleRoundedCurveCustomStyle": {
              "expr": {
                "Literal": {
                  "Value": "false"
                }
              }
            },
            "rectangleRoundedCurveLeftTop": {
              "expr": {
                "Literal": {
                  "Value": "26L"
                }
              }
            },
            "rectangleRoundedCurveRightTop": {
              "expr": {
                "Literal": {
                  "Value": "14L"
                }
              }
            },
            "rectangleRoundedCurveLeftBottom": {
              "expr": {
                "Literal": {
                  "Value": "37L"
                }
              }
            },
            "rectangleRoundedCurveRightBottom": {
              "expr": {
                "Literal": {
                  "Value": "35L"
                }
              }
            },
            "backgroundShow": {
              "expr": {
                "Literal": {
                  "Value": "false"
                }
              }
            },
            "backgroundFillColor": {
              "solid": {
                "color": {
                  "expr": {
                    "ThemeDataColor": {
                      "ColorId": 0,
                      "Percent": 0
                    }
                  }
                }
              }
            }
          },
          "selector": {
            "id": "default"
          }
        }
      ],
      "border": [
        {
          "properties": {
            "show": {
              "expr": {
                "Literal": {
                  "Value": "false"
                }
              }
            },
            "color": {
              "solid": {
                "color": {
                  "expr": {
                    "ThemeDataColor": {
                      "ColorId": 0,
                      "Percent": 0
                    }
                  }
                }
              }
            },
            "transparency": {
              "expr": {
                "Literal": {
                  "Value": "0D"
                }
              }
            },
            "style": {
              "expr": {
                "Literal": {
                  "Value": "'solid'"
                }
              }
            }
          },
          "selector": {
            "id": "default"
          }
        }
      ],
      "value": [
        {
          "properties": {
            "fontFamily": {
              "expr": {
                "Literal": {
                  "Value": "'''Segoe UI Bold'', wf_segoe-ui_bold, helvetica, arial, sans-serif'"
                }
              }
            },
            "horizontalAlignment": {
              "expr": {
                "Literal": {
                  "Value": "'center'"
                }
              }
            },
            "textWrap": {
              "expr": {
                "Literal": {
                  "Value": "false"
                }
              }
            }
          },
          "selector": {
            "id": "default"
          }
        }
      ],
      "label": [
        {
          "properties": {
            "show": {
              "expr": {
                "Literal": {
                  "Value": "true"
                }
              }
            },
            "fontFamily": {
              "expr": {
                "Literal": {
                  "Value": "'''Segoe UI Bold'', wf_segoe-ui_bold, helvetica, arial, sans-serif'"
                }
              }
            }
          },
          "selector": {
            "id": "default"
          }
        },
        {
          "properties": {
            "text": {
              "expr": {
                "Literal": {
                  "Value": "'TOTAL QUANTITY SOLD'"
                }
              }
            }
          },
          "selector": {
            "metadata": "Sum(cleaned_dataset.quantity_sold)"
          }
        },
        {
          "properties": {
            "text": {
              "expr": {
                "Literal": {
                  "Value": "'TOTAL REVENUE'"
                }
              }
            }
          },
          "selector": {
            "metadata": "Sum(cleaned_dataset.total_revenue)"
          }
        },
        {
          "properties": {
            "text": {
              "expr": {
                "Literal": {
                  "Value": "'TOTAL PROFIT'"
                }
              }
            }
          },
          "selector": {
            "metadata": "Sum(cleaned_dataset.profit)"
          }
        }
      ],
      "referenceLabel": [
        {
          "properties": {},
          "selector": {
            "data": [
              {
                "dataViewWildcard": {
                  "matchingOption": 0
                }
              }
            ],
            "metadata": "Sum(cleaned_dataset.total_revenue)",
            "id": "field-5dae4082-c58b-2f04-7c0b-f29a7fa0cc0f",
            "order": 0
          }
        }
      ],
      "shapeCustomRectangle": [
        {
          "properties": {
            "tileShape": {
              "expr": {
                "Literal": {
                  "Value": "'rectangleRoundedByPixel'"
                }
              }
            },
            "rectangleRoundedCurveCustomStyle": {
              "expr": {
                "Literal": {
                  "Value": "false"
                }
              }
            }
          },
          "selector": {
            "id": "default"
          }
        }
      ],
      "fillCustom": [
        {
          "properties": {
            "fillColor": {
              "solid": {
                "color": {
                  "expr": {
                    "Literal": {
                      "Value": "'#e66c37'"
                    }
                  }
                }
              }
            }
          },
          "selector": {
            "id": "default"
          }
        }
      ],
      "shadowCustom": [
        {
          "properties": {
            "show": {
              "expr": {
                "Literal": {
                  "Value": "true"
                }
              }
            }
          },
          "selector": {
            "id": "default"
          }
        }
      ],
      "glowCustom": [
        {
          "properties": {
            "show": {
              "expr": {
                "Literal": {
                  "Value": "true"
                }
              }
            },
            "color": {
              "solid": {
                "color": {
                  "expr": {
                    "Literal": {
                      "Value": "'#e66c37'"
                    }
                  }
                }
              }
            }
          },
          "selector": {
            "id": "default"
          }
        }
      ]
    },
    "visualContainerObjects": {
      "dropShadow": [
        {
          "properties": {
            "show": {
              "expr": {
                "Literal": {
                  "Value": "false"
                }
              }
            }
          }
        }
      ],
      "background": [
        {
          "properties": {
            "color": {
              "solid": {
                "color": {
                  "expr": {
                    "ThemeDataColor": {
                      "ColorId": 0,
                      "Percent": 0
                    }
                  }
                }
              }
            }
          }
        }
      ]
    },
    "drillFilterOtherVisuals": true
  }
}